capturing_process/__init__.py
capturing_process/capturing_process.py
capturing_process/stream_thread.py
capturing_process-1.0.13.dist-info/LICENSE
capturing_process-1.0.13.dist-info/METADATA
capturing_process-1.0.13.dist-info/WHEEL
capturing_process-1.0.13.dist-info/top_level.txt
capturing_process-1.0.13.dist-info/RECORD
