Metadata-Version: 2.1
Name: capturing-process
Version: 1.0.13
Summary: Captures stderr/stdout as a stream to allow easy log monitoring of long running shell processes.",
Home-page: https://github.com/zackees/capturing_process
Author: Zach Vorhies
Author-email: dont@email.me
License: MIT
Classifier: License :: OSI Approved :: MIT License
Classifier: Programming Language :: Python :: 3
Classifier: Programming Language :: Python :: 3.7
Requires-Python: >=3.6.0
License-File: LICENSE
Requires-Dist: colorama ; sys_platform == "win32"
